.gitignore
LICENSE
README.md
requirements.txt
setup.cfg
setup.py
temp_test2/__init__.py
temp_test2/__main__.py
temp_test2.egg-info/PKG-INFO
temp_test2.egg-info/SOURCES.txt
temp_test2.egg-info/dependency_links.txt
temp_test2.egg-info/entry_points.txt
temp_test2.egg-info/not-zip-safe
temp_test2.egg-info/requires.txt
temp_test2.egg-info/top_level.txt