Metadata-Version: 1.1
Name: temp-test2
Version: 0.1.4
Summary: test module
Home-page: https://github.com/jtara1/temp_test2
Author: jtara1
Author-email: UNKNOWN
License: MIT
Download-URL: https://github.com/jtara1/temp_test2/archive/0.1.1.tar.gz
Keywords: imgur,downloader
Platform: UNKNOWN
Classifier: Programming Language :: Python
Classifier: Programming Language :: Python :: 3.5
